dmm/__init__.py
dmm/argument_parser.py
dmm/batch_metric_evaluator.py
dmm/constants.py
dmm/custom_metric.py
dmm/datarobot_api_client.py
dmm/example_data_helper.py
dmm/exceptions.py
dmm/individual_metric_evaluator.py
dmm/log_manager.py
dmm/metric_evaluator.py
dmm/time_bucket.py
dmm/utils.py
dmm/data_source/__init__.py
dmm/data_source/data_source_base.py
dmm/data_source/dataframe_source.py
dmm/data_source/datarobot_source.py
dmm/data_source/generator_source.py
dmm/data_source/runtime_parameters_source.py
dmm/data_source/datarobot/__init__.py
dmm/data_source/datarobot/deployment.py
dmm/data_source/datarobot/export_provider.py
dmm/dr_custom_metrics/__init__.py
dmm/dr_custom_metrics/deployment_event_reporter.py
dmm/dr_custom_metrics/dr_custom_metric.py
dmm/metric/__init__.py
dmm/metric/asymmetric_error.py
dmm/metric/geo_metrics.py
dmm/metric/median_absolute_error.py
dmm/metric/metric_base.py
dmm/metric/missing_values.py
dmm/metric/prompt_similarity.py
dmm/metric/sklearn_metric.py
datarobot_model_metrics-0.6.14.dist-info/METADATA
datarobot_model_metrics-0.6.14.dist-info/WHEEL
datarobot_model_metrics-0.6.14.dist-info/top_level.txt
datarobot_model_metrics-0.6.14.dist-info/RECORD
