Metadata-Version: 2.4
Name: datarobot-model-metrics
Version: 0.6.14
Summary: datarobot-model-metrics provides a framework to compute model ML metrics over time and produce aggregated metrics.
Home-page: https://github.com/datarobot/datarobot-model-metrics
Author: DataRobot
Author-email: info@datarobot.com
License: DataRobot
Classifier: Programming Language :: Python :: 3
Classifier: Programming Language :: Python :: 3.7
Classifier: License :: OSI Approved :: Apache Software License
Classifier: Operating System :: MacOS
Classifier: Operating System :: POSIX
Classifier: Operating System :: Unix
Requires-Python: >=3.7
Requires-Dist: numpy
Requires-Dist: pandas
Requires-Dist: scikit-learn
Requires-Dist: datarobot
Requires-Dist: schema
Requires-Dist: typing-extensions==4.12.2
Dynamic: author
Dynamic: author-email
Dynamic: classifier
Dynamic: description
Dynamic: description-content-type
Dynamic: home-page
Dynamic: license
Dynamic: requires-dist
Dynamic: requires-python
Dynamic: summary
